{
  "id": "19057",
  "name": "Nicola Mccoy",
  "sex": "Female",
  "category": "Vet",
  "club": "Muckle Cycle Club",
  "inBAR": true,
  "inVBAR": true,
  "inWBAR": true,
  "inWVBAR": true,
  "inRBAR": true,
  "inWRBAR": true,
  "bar": {
    "short": [
      {
        "eventId": "18264",
        "raceCategory": "short",
        "name": "Barnesbury CC (Cheques To S Dodd)",
        "course": "M102C",
        "distance": 10,
        "fee": 10,
        "date": "18 August 2019",
        "club": "Muckle Cycle Club",
        "position": "58",
        "time": "0:28:02",
        "standard": "00:29:21",
        "onStandard": "-00:01:19",
        "speed": "21.40 Mph",
        "bar": 77,
        "barPosition": 44,
        "vbar": 99,
        "vbarPosition": 22,
        "wvbar": 118,
        "wvbarPosition": 3,
        "wbar": 114,
        "wbarPosition": 7,
        "rbar": 0,
        "rbarPosition": 0,
        "wrbar": 0,
        "wrbarPosition": 0
      },
      {
        "eventId": "18247",
        "raceCategory": "short",
        "name": "Alnwick CC",
        "course": "M13",
        "distance": 13,
        "fee": 11,
        "date": "01 June 2019",
        "club": "Muckle Cycle Club",
        "position": "60",
        "time": "0:36:39",
        "standard": "00:38:17",
        "onStandard": "-00:01:38",
        "speed": "21.28 Mph",
        "bar": 75,
        "barPosition": 46,
        "vbar": 104,
        "vbarPosition": 17,
        "wvbar": 117,
        "wvbarPosition": 4,
        "wbar": 113,
        "wbarPosition": 8,
        "rbar": 0,
        "rbarPosition": 0,
        "wrbar": 0,
        "wrbarPosition": 0
      },
      {
        "eventId": "18256",
        "raceCategory": "short",
        "name": "Barnesbury CC (Cheques To B Bayne)(80 Riders)",
        "course": "M102B",
        "distance": 10,
        "fee": 10,
        "date": "10 July 2019",
        "club": "Muckle Cycle Club",
        "position": "59",
        "time": "0:25:31",
        "standard": "00:29:21",
        "onStandard": "-00:03:50",
        "speed": "23.51 Mph",
        "bar": 70,
        "barPosition": 51,
        "vbar": 99,
        "vbarPosition": 22,
        "wvbar": 118,
        "wvbarPosition": 3,
        "wbar": 116,
        "wbarPosition": 5,
        "rbar": 0,
        "rbarPosition": 0,
        "wrbar": 0,
        "wrbarPosition": 0
      }
    ],
    "medium": [
      {
        "eventId": "18246",
        "raceCategory": "medium",
        "name": "North Tyneside Riders",
        "course": "M27",
        "distance": 27,
        "fee": 11,
        "date": "07 July 2019",
        "club": "Muckle Cycle Club",
        "position": "26",
        "time": "1:41:59",
        "standard": "01:20:38",
        "onStandard": "00:21:21",
        "speed": "15.88 Mph",
        "bar": 98,
        "barPosition": 23,
        "vbar": 107,
        "vbarPosition": 14,
        "wvbar": 119,
        "wvbarPosition": 2,
        "wbar": 118,
        "wbarPosition": 3,
        "rbar": 112,
        "rbarPosition": 9,
        "wrbar": 118,
        "wrbarPosition": 3
      },
      {
        "eventId": "18260",
        "raceCategory": "medium",
        "name": "GS Metro",
        "course": "M26",
        "distance": 26,
        "fee": 11,
        "date": "27 July 2019",
        "club": "Muckle Cycle Club",
        "position": "35",
        "time": "1:19:50",
        "standard": "01:17:34",
        "onStandard": "00:02:16",
        "speed": "19.54 Mph",
        "bar": 90,
        "barPosition": 31,
        "vbar": 109,
        "vbarPosition": 12,
        "wvbar": 119,
        "wvbarPosition": 2,
        "wbar": 115,
        "wbarPosition": 6,
        "rbar": 0,
        "rbarPosition": 0,
        "wrbar": 0,
        "wrbarPosition": 0
      }
    ],
    "long": [
      {
        "eventId": "18263",
        "raceCategory": "long",
        "name": "South Shields Velo CC (N&DCA Championship) (BBAR)",
        "course": "M5011",
        "distance": 50,
        "fee": 11,
        "date": "04 August 2019",
        "club": "Muckle Cycle Club",
        "position": "53",
        "time": "2:27:20",
        "standard": "02:32:43",
        "onStandard": "-00:05:23",
        "speed": "20.36 Mph",
        "bar": 71,
        "barPosition": 50,
        "vbar": 97,
        "vbarPosition": 24,
        "wvbar": 117,
        "wvbarPosition": 4,
        "wbar": 115,
        "wbarPosition": 6,
        "rbar": 0,
        "rbarPosition": 0,
        "wrbar": 0,
        "wrbarPosition": 0
      }
    ],
    "shortCount": 3,
    "mediumCount": 2,
    "longCount": 1,
    "allCount": 6,
    "complete": true,
    "canComplete": true,
    "averagePointsPerShortRace": 74,
    "averagePointsPerMediumRace": 94,
    "averagePointsPerLongRace": 71,
    "averagePointsPerRace": 80.16666666666667,
    "remainingShortPoints": 138,
    "remainingMediumPoints": 52,
    "remainingLongPoints": 49,
    "remainingPoints": 239,
    "predictedFinalPoints": 481,
    "pointsDirection": 0,
    "regionalChampionship": {
      "raced": 2,
      "totalPoints": 71
    },
    "tieBreak": {
      "raced": 3,
      "totalPoints": 215
    },
    "totals": {
      "short": 222,
      "medium": 188,
      "long": 71,
      "grand": 481
    },
    "tags": [
      {
        "cssclass": "tag is-black",
        "text": "1 x DNS"
      }
    ],
    "currentPosition": 59,
    "rivals": [
      {
        "position": 1,
        "id": "8323",
        "pointsDirection": 0,
        "barPredictedFinalPosition": 1,
        "name": "Lewis Timmins",
        "club": "Team Swift",
        "averagePointsPerRace": 119.83333333333333,
        "predictedFinalPoints": 719,
        "grandTotal": 719,
        "complete": true,
        "canComplete": true,
        "regionalChampionshipPoints": 345,
        "tieBreakPoints": 227
      },
      {
        "position": 56,
        "id": "3838",
        "pointsDirection": 0,
        "barPredictedFinalPosition": 56,
        "name": "Gemma Hutchins",
        "club": "Blaydon CC",
        "averagePointsPerRace": 85.66666666666667,
        "predictedFinalPoints": 514,
        "grandTotal": 514,
        "complete": true,
        "canComplete": true,
        "regionalChampionshipPoints": 81,
        "tieBreakPoints": 143
      },
      {
        "position": 57,
        "id": "3297",
        "pointsDirection": 0,
        "barPredictedFinalPosition": 57,
        "name": "Paul Barrett",
        "club": "Wearside Triathlon",
        "averagePointsPerRace": 85,
        "predictedFinalPoints": 510,
        "grandTotal": 510,
        "complete": true,
        "canComplete": true,
        "regionalChampionshipPoints": 0,
        "tieBreakPoints": 0
      },
      {
        "position": 58,
        "id": "18735",
        "pointsDirection": 0,
        "barPredictedFinalPosition": 58,
        "name": "James George Dunn",
        "club": "South Shields Velo Cycling Club",
        "averagePointsPerRace": 81.33333333333333,
        "predictedFinalPoints": 488,
        "grandTotal": 488,
        "complete": true,
        "canComplete": true,
        "regionalChampionshipPoints": 82,
        "tieBreakPoints": 136
      },
      {
        "position": 59,
        "id": "19057",
        "pointsDirection": 0,
        "barPredictedFinalPosition": 59,
        "name": "Nicola Mccoy",
        "club": "Muckle Cycle Club",
        "averagePointsPerRace": 80.16666666666667,
        "predictedFinalPoints": 481,
        "grandTotal": 481,
        "complete": true,
        "canComplete": true,
        "regionalChampionshipPoints": 71,
        "tieBreakPoints": 215
      },
      {
        "position": 60,
        "id": "4497",
        "pointsDirection": 0,
        "barPredictedFinalPosition": 60,
        "name": "Raymond Bell",
        "club": "Derwentside CC",
        "averagePointsPerRace": 79.5,
        "predictedFinalPoints": 477,
        "grandTotal": 477,
        "complete": true,
        "canComplete": true,
        "regionalChampionshipPoints": 75,
        "tieBreakPoints": 113
      },
      {
        "position": 61,
        "id": "92",
        "pointsDirection": 0,
        "barPredictedFinalPosition": 61,
        "name": "Mick Chappel",
        "club": "North Tyneside Riders CC",
        "averagePointsPerRace": 78.33333333333333,
        "predictedFinalPoints": 470,
        "grandTotal": 470,
        "complete": true,
        "canComplete": true,
        "regionalChampionshipPoints": 68,
        "tieBreakPoints": 68
      },
      {
        "position": 62,
        "id": "96",
        "pointsDirection": 0,
        "barPredictedFinalPosition": 62,
        "name": "Richard Exley",
        "club": "Gosforth RC",
        "averagePointsPerRace": 77,
        "predictedFinalPoints": 462,
        "grandTotal": 462,
        "complete": true,
        "canComplete": true,
        "regionalChampionshipPoints": 73,
        "tieBreakPoints": 73
      }
    ]
  },
  "vbar": {
    "short": [
      {
        "eventId": "18247",
        "raceCategory": "short",
        "name": "Alnwick CC",
        "course": "M13",
        "distance": 13,
        "fee": 11,
        "date": "01 June 2019",
        "club": "Muckle Cycle Club",
        "position": "60",
        "time": "0:36:39",
        "standard": "00:38:17",
        "onStandard": "-00:01:38",
        "speed": "21.28 Mph",
        "bar": 75,
        "barPosition": 46,
        "vbar": 104,
        "vbarPosition": 17,
        "wvbar": 117,
        "wvbarPosition": 4,
        "wbar": 113,
        "wbarPosition": 8,
        "rbar": 0,
        "rbarPosition": 0,
        "wrbar": 0,
        "wrbarPosition": 0
      },
      {
        "eventId": "18256",
        "raceCategory": "short",
        "name": "Barnesbury CC (Cheques To B Bayne)(80 Riders)",
        "course": "M102B",
        "distance": 10,
        "fee": 10,
        "date": "10 July 2019",
        "club": "Muckle Cycle Club",
        "position": "59",
        "time": "0:25:31",
        "standard": "00:29:21",
        "onStandard": "-00:03:50",
        "speed": "23.51 Mph",
        "bar": 70,
        "barPosition": 51,
        "vbar": 99,
        "vbarPosition": 22,
        "wvbar": 118,
        "wvbarPosition": 3,
        "wbar": 116,
        "wbarPosition": 5,
        "rbar": 0,
        "rbarPosition": 0,
        "wrbar": 0,
        "wrbarPosition": 0
      },
      {
        "eventId": "18264",
        "raceCategory": "short",
        "name": "Barnesbury CC (Cheques To S Dodd)",
        "course": "M102C",
        "distance": 10,
        "fee": 10,
        "date": "18 August 2019",
        "club": "Muckle Cycle Club",
        "position": "58",
        "time": "0:28:02",
        "standard": "00:29:21",
        "onStandard": "-00:01:19",
        "speed": "21.40 Mph",
        "bar": 77,
        "barPosition": 44,
        "vbar": 99,
        "vbarPosition": 22,
        "wvbar": 118,
        "wvbarPosition": 3,
        "wbar": 114,
        "wbarPosition": 7,
        "rbar": 0,
        "rbarPosition": 0,
        "wrbar": 0,
        "wrbarPosition": 0
      }
    ],
    "medium": [
      {
        "eventId": "18260",
        "raceCategory": "medium",
        "name": "GS Metro",
        "course": "M26",
        "distance": 26,
        "fee": 11,
        "date": "27 July 2019",
        "club": "Muckle Cycle Club",
        "position": "35",
        "time": "1:19:50",
        "standard": "01:17:34",
        "onStandard": "00:02:16",
        "speed": "19.54 Mph",
        "bar": 90,
        "barPosition": 31,
        "vbar": 109,
        "vbarPosition": 12,
        "wvbar": 119,
        "wvbarPosition": 2,
        "wbar": 115,
        "wbarPosition": 6,
        "rbar": 0,
        "rbarPosition": 0,
        "wrbar": 0,
        "wrbarPosition": 0
      },
      {
        "eventId": "18246",
        "raceCategory": "medium",
        "name": "North Tyneside Riders",
        "course": "M27",
        "distance": 27,
        "fee": 11,
        "date": "07 July 2019",
        "club": "Muckle Cycle Club",
        "position": "26",
        "time": "1:41:59",
        "standard": "01:20:38",
        "onStandard": "00:21:21",
        "speed": "15.88 Mph",
        "bar": 98,
        "barPosition": 23,
        "vbar": 107,
        "vbarPosition": 14,
        "wvbar": 119,
        "wvbarPosition": 2,
        "wbar": 118,
        "wbarPosition": 3,
        "rbar": 112,
        "rbarPosition": 9,
        "wrbar": 118,
        "wrbarPosition": 3
      }
    ],
    "long": [
      {
        "eventId": "18263",
        "raceCategory": "long",
        "name": "South Shields Velo CC (N&DCA Championship) (BBAR)",
        "course": "M5011",
        "distance": 50,
        "fee": 11,
        "date": "04 August 2019",
        "club": "Muckle Cycle Club",
        "position": "53",
        "time": "2:27:20",
        "standard": "02:32:43",
        "onStandard": "-00:05:23",
        "speed": "20.36 Mph",
        "bar": 71,
        "barPosition": 50,
        "vbar": 97,
        "vbarPosition": 24,
        "wvbar": 117,
        "wvbarPosition": 4,
        "wbar": 115,
        "wbarPosition": 6,
        "rbar": 0,
        "rbarPosition": 0,
        "wrbar": 0,
        "wrbarPosition": 0
      }
    ],
    "shortCount": 3,
    "mediumCount": 2,
    "longCount": 1,
    "allCount": 6,
    "complete": true,
    "canComplete": true,
    "averagePointsPerShortRace": 100.66666666666667,
    "averagePointsPerMediumRace": 108,
    "averagePointsPerLongRace": 97,
    "averagePointsPerRace": 102.5,
    "remainingShortPoints": 58,
    "remainingMediumPoints": 24,
    "remainingLongPoints": 23,
    "remainingPoints": 105,
    "predictedFinalPoints": 615,
    "pointsDirection": 1,
    "regionalChampionship": {
      "raced": 2,
      "totalPoints": 97
    },
    "tieBreak": {
      "raced": 3,
      "totalPoints": 286
    },
    "totals": {
      "short": 302,
      "medium": 216,
      "long": 97,
      "grand": 615
    },
    "tags": [
      {
        "cssclass": "tag is-black",
        "text": "1 x DNS"
      }
    ],
    "currentPosition": 28,
    "rivals": [
      {
        "position": 1,
        "id": "2041",
        "pointsDirection": 0,
        "barPredictedFinalPosition": 1,
        "name": "Philip Kennell",
        "club": "GS Metro",
        "averagePointsPerRace": 119.5,
        "predictedFinalPoints": 717,
        "grandTotal": 717,
        "complete": true,
        "canComplete": true,
        "regionalChampionshipPoints": 476,
        "tieBreakPoints": 349
      },
      {
        "position": 25,
        "id": "6666",
        "pointsDirection": -3,
        "barPredictedFinalPosition": 25,
        "name": "David Swainson",
        "club": "Derwentside CC",
        "averagePointsPerRace": 105,
        "predictedFinalPoints": 630,
        "grandTotal": 630,
        "complete": true,
        "canComplete": true,
        "regionalChampionshipPoints": 313,
        "tieBreakPoints": 191
      },
      {
        "position": 26,
        "id": "2980",
        "pointsDirection": 2,
        "barPredictedFinalPosition": 27,
        "name": "Paul Robson",
        "club": "Houghton CC",
        "averagePointsPerRace": 104,
        "predictedFinalPoints": 624,
        "grandTotal": 624,
        "complete": true,
        "canComplete": true,
        "regionalChampionshipPoints": 204,
        "tieBreakPoints": 98
      },
      {
        "position": 27,
        "id": "25152",
        "pointsDirection": 1,
        "barPredictedFinalPosition": 28,
        "name": "John Cantrill",
        "club": "Blaydon CC",
        "averagePointsPerRace": 102.83333333333333,
        "predictedFinalPoints": 617,
        "grandTotal": 617,
        "complete": true,
        "canComplete": true,
        "regionalChampionshipPoints": 0,
        "tieBreakPoints": 177
      },
      {
        "position": 28,
        "id": "19057",
        "pointsDirection": 1,
        "barPredictedFinalPosition": 29,
        "name": "Nicola Mccoy",
        "club": "Muckle Cycle Club",
        "averagePointsPerRace": 102.5,
        "predictedFinalPoints": 615,
        "grandTotal": 615,
        "complete": true,
        "canComplete": true,
        "regionalChampionshipPoints": 97,
        "tieBreakPoints": 286
      },
      {
        "position": 29,
        "id": "4497",
        "pointsDirection": 0,
        "barPredictedFinalPosition": 30,
        "name": "Raymond Bell",
        "club": "Derwentside CC",
        "averagePointsPerRace": 101.16666666666667,
        "predictedFinalPoints": 607,
        "grandTotal": 607,
        "complete": true,
        "canComplete": true,
        "regionalChampionshipPoints": 102,
        "tieBreakPoints": 171
      },
      {
        "position": 30,
        "id": "11708",
        "pointsDirection": 0,
        "barPredictedFinalPosition": 31,
        "name": "Howie Buckingham",
        "club": "Allen Valley Velo",
        "averagePointsPerRace": 99.83333333333333,
        "predictedFinalPoints": 599,
        "grandTotal": 599,
        "complete": true,
        "canComplete": true,
        "regionalChampionshipPoints": 96,
        "tieBreakPoints": 108
      },
      {
        "position": 31,
        "id": "7743",
        "pointsDirection": 0,
        "barPredictedFinalPosition": 32,
        "name": "Stephen Mcintosh",
        "club": "Barnesbury CC",
        "averagePointsPerRace": 95.66666666666667,
        "predictedFinalPoints": 574,
        "grandTotal": 574,
        "complete": true,
        "canComplete": true,
        "regionalChampionshipPoints": 183,
        "tieBreakPoints": 0
      }
    ]
  },
  "wbar": {
    "short": [
      {
        "eventId": "18256",
        "raceCategory": "short",
        "name": "Barnesbury CC (Cheques To B Bayne)(80 Riders)",
        "course": "M102B",
        "distance": 10,
        "fee": 10,
        "date": "10 July 2019",
        "club": "Muckle Cycle Club",
        "position": "59",
        "time": "0:25:31",
        "standard": "00:29:21",
        "onStandard": "-00:03:50",
        "speed": "23.51 Mph",
        "bar": 70,
        "barPosition": 51,
        "vbar": 99,
        "vbarPosition": 22,
        "wvbar": 118,
        "wvbarPosition": 3,
        "wbar": 116,
        "wbarPosition": 5,
        "rbar": 0,
        "rbarPosition": 0,
        "wrbar": 0,
        "wrbarPosition": 0
      },
      {
        "eventId": "18264",
        "raceCategory": "short",
        "name": "Barnesbury CC (Cheques To S Dodd)",
        "course": "M102C",
        "distance": 10,
        "fee": 10,
        "date": "18 August 2019",
        "club": "Muckle Cycle Club",
        "position": "58",
        "time": "0:28:02",
        "standard": "00:29:21",
        "onStandard": "-00:01:19",
        "speed": "21.40 Mph",
        "bar": 77,
        "barPosition": 44,
        "vbar": 99,
        "vbarPosition": 22,
        "wvbar": 118,
        "wvbarPosition": 3,
        "wbar": 114,
        "wbarPosition": 7,
        "rbar": 0,
        "rbarPosition": 0,
        "wrbar": 0,
        "wrbarPosition": 0
      },
      {
        "eventId": "18247",
        "raceCategory": "short",
        "name": "Alnwick CC",
        "course": "M13",
        "distance": 13,
        "fee": 11,
        "date": "01 June 2019",
        "club": "Muckle Cycle Club",
        "position": "60",
        "time": "0:36:39",
        "standard": "00:38:17",
        "onStandard": "-00:01:38",
        "speed": "21.28 Mph",
        "bar": 75,
        "barPosition": 46,
        "vbar": 104,
        "vbarPosition": 17,
        "wvbar": 117,
        "wvbarPosition": 4,
        "wbar": 113,
        "wbarPosition": 8,
        "rbar": 0,
        "rbarPosition": 0,
        "wrbar": 0,
        "wrbarPosition": 0
      }
    ],
    "medium": [
      {
        "eventId": "18246",
        "raceCategory": "medium",
        "name": "North Tyneside Riders",
        "course": "M27",
        "distance": 27,
        "fee": 11,
        "date": "07 July 2019",
        "club": "Muckle Cycle Club",
        "position": "26",
        "time": "1:41:59",
        "standard": "01:20:38",
        "onStandard": "00:21:21",
        "speed": "15.88 Mph",
        "bar": 98,
        "barPosition": 23,
        "vbar": 107,
        "vbarPosition": 14,
        "wvbar": 119,
        "wvbarPosition": 2,
        "wbar": 118,
        "wbarPosition": 3,
        "rbar": 112,
        "rbarPosition": 9,
        "wrbar": 118,
        "wrbarPosition": 3
      },
      {
        "eventId": "18252",
        "raceCategory": "medium",
        "name": "Houghton CC (BBAR)",
        "course": "M254",
        "distance": 25,
        "fee": 11,
        "date": "23 June 2019",
        "club": "Muckle Cycle Club",
        "position": "36",
        "time": "1:12:22",
        "standard": "01:14:31",
        "onStandard": "-00:02:09",
        "speed": "20.73 Mph",
        "bar": 87,
        "barPosition": 34,
        "vbar": 103,
        "vbarPosition": 18,
        "wvbar": 118,
        "wvbarPosition": 3,
        "wbar": 117,
        "wbarPosition": 4,
        "rbar": 0,
        "rbarPosition": 0,
        "wrbar": 0,
        "wrbarPosition": 0
      }
    ],
    "long": [
      {
        "eventId": "18263",
        "raceCategory": "long",
        "name": "South Shields Velo CC (N&DCA Championship) (BBAR)",
        "course": "M5011",
        "distance": 50,
        "fee": 11,
        "date": "04 August 2019",
        "club": "Muckle Cycle Club",
        "position": "53",
        "time": "2:27:20",
        "standard": "02:32:43",
        "onStandard": "-00:05:23",
        "speed": "20.36 Mph",
        "bar": 71,
        "barPosition": 50,
        "vbar": 97,
        "vbarPosition": 24,
        "wvbar": 117,
        "wvbarPosition": 4,
        "wbar": 115,
        "wbarPosition": 6,
        "rbar": 0,
        "rbarPosition": 0,
        "wrbar": 0,
        "wrbarPosition": 0
      }
    ],
    "shortCount": 3,
    "mediumCount": 2,
    "longCount": 1,
    "allCount": 6,
    "complete": true,
    "canComplete": true,
    "averagePointsPerShortRace": 114.33333333333333,
    "averagePointsPerMediumRace": 117.5,
    "averagePointsPerLongRace": 115,
    "averagePointsPerRace": 115.5,
    "remainingShortPoints": 17,
    "remainingMediumPoints": 5,
    "remainingLongPoints": 5,
    "remainingPoints": 27,
    "predictedFinalPoints": 693,
    "pointsDirection": 0,
    "regionalChampionship": {
      "raced": 2,
      "totalPoints": 115
    },
    "tieBreak": {
      "raced": 3,
      "totalPoints": 344
    },
    "totals": {
      "short": 343,
      "medium": 235,
      "long": 115,
      "grand": 693
    },
    "tags": [
      {
        "cssclass": "tag has-background-warning",
        "text": "1 x 3rd WBAR"
      },
      {
        "cssclass": "tag has-background-warning",
        "text": "5 x Top 5 WBAR"
      },
      {
        "cssclass": "tag has-background-warning",
        "text": "13 x Top 10 WBAR"
      },
      {
        "cssclass": "tag is-black",
        "text": "1 x DNS"
      }
    ],
    "currentPosition": 10,
    "rivals": [
      {
        "position": 1,
        "id": "16184",
        "pointsDirection": 0,
        "barPredictedFinalPosition": 1,
        "name": "Gemma Frost",
        "club": "Team Swift",
        "averagePointsPerRace": 120,
        "predictedFinalPoints": 720,
        "grandTotal": 720,
        "complete": true,
        "canComplete": true,
        "regionalChampionshipPoints": 359,
        "tieBreakPoints": 239
      },
      {
        "position": 7,
        "id": "3838",
        "pointsDirection": 0,
        "barPredictedFinalPosition": 7,
        "name": "Gemma Hutchins",
        "club": "Blaydon CC",
        "averagePointsPerRace": 117.16666666666667,
        "predictedFinalPoints": 703,
        "grandTotal": 703,
        "complete": true,
        "canComplete": true,
        "regionalChampionshipPoints": 116,
        "tieBreakPoints": 233
      },
      {
        "position": 8,
        "id": "22857",
        "pointsDirection": 0,
        "barPredictedFinalPosition": 8,
        "name": "Rachel Galler",
        "club": "Blaydon CC",
        "averagePointsPerRace": 117.16666666666667,
        "predictedFinalPoints": 703,
        "grandTotal": 703,
        "complete": true,
        "canComplete": true,
        "regionalChampionshipPoints": 0,
        "tieBreakPoints": 116
      },
      {
        "position": 9,
        "id": "3419",
        "pointsDirection": 0,
        "barPredictedFinalPosition": 9,
        "name": "Teri Bayliss",
        "club": "Muckle Cycle Club",
        "averagePointsPerRace": 116.66666666666667,
        "predictedFinalPoints": 700,
        "grandTotal": 700,
        "complete": true,
        "canComplete": true,
        "regionalChampionshipPoints": 233,
        "tieBreakPoints": 230
      },
      {
        "position": 10,
        "id": "19057",
        "pointsDirection": 0,
        "barPredictedFinalPosition": 10,
        "name": "Nicola Mccoy",
        "club": "Muckle Cycle Club",
        "averagePointsPerRace": 115.5,
        "predictedFinalPoints": 693,
        "grandTotal": 693,
        "complete": true,
        "canComplete": true,
        "regionalChampionshipPoints": 115,
        "tieBreakPoints": 344
      },
      {
        "position": 11,
        "id": "2846",
        "pointsDirection": 0,
        "barPredictedFinalPosition": 11,
        "name": "Justine Norman",
        "club": "Breeze Bikes RT",
        "averagePointsPerRace": 113.5,
        "predictedFinalPoints": 681,
        "grandTotal": 681,
        "complete": true,
        "canComplete": true,
        "regionalChampionshipPoints": 114,
        "tieBreakPoints": 226
      },
      {
        "position": 12,
        "id": "9698",
        "pointsDirection": 0,
        "barPredictedFinalPosition": 12,
        "name": "Tracey Sample",
        "club": "Breeze Bikes RT",
        "averagePointsPerRace": 113,
        "predictedFinalPoints": 678,
        "grandTotal": 678,
        "complete": true,
        "canComplete": true,
        "regionalChampionshipPoints": 113,
        "tieBreakPoints": 113
      },
      {
        "position": 13,
        "id": "16749",
        "pointsDirection": 0,
        "barPredictedFinalPosition": 13,
        "name": "Jane Aston",
        "club": "Blaydon CC",
        "averagePointsPerRace": 110.83333333333333,
        "predictedFinalPoints": 665,
        "grandTotal": 665,
        "complete": true,
        "canComplete": true,
        "regionalChampionshipPoints": 0,
        "tieBreakPoints": 223
      }
    ]
  },
  "wvbar": {
    "short": [
      {
        "eventId": "18256",
        "raceCategory": "short",
        "name": "Barnesbury CC (Cheques To B Bayne)(80 Riders)",
        "course": "M102B",
        "distance": 10,
        "fee": 10,
        "date": "10 July 2019",
        "club": "Muckle Cycle Club",
        "position": "59",
        "time": "0:25:31",
        "standard": "00:29:21",
        "onStandard": "-00:03:50",
        "speed": "23.51 Mph",
        "bar": 70,
        "barPosition": 51,
        "vbar": 99,
        "vbarPosition": 22,
        "wvbar": 118,
        "wvbarPosition": 3,
        "wbar": 116,
        "wbarPosition": 5,
        "rbar": 0,
        "rbarPosition": 0,
        "wrbar": 0,
        "wrbarPosition": 0
      },
      {
        "eventId": "18264",
        "raceCategory": "short",
        "name": "Barnesbury CC (Cheques To S Dodd)",
        "course": "M102C",
        "distance": 10,
        "fee": 10,
        "date": "18 August 2019",
        "club": "Muckle Cycle Club",
        "position": "58",
        "time": "0:28:02",
        "standard": "00:29:21",
        "onStandard": "-00:01:19",
        "speed": "21.40 Mph",
        "bar": 77,
        "barPosition": 44,
        "vbar": 99,
        "vbarPosition": 22,
        "wvbar": 118,
        "wvbarPosition": 3,
        "wbar": 114,
        "wbarPosition": 7,
        "rbar": 0,
        "rbarPosition": 0,
        "wrbar": 0,
        "wrbarPosition": 0
      },
      {
        "eventId": "18247",
        "raceCategory": "short",
        "name": "Alnwick CC",
        "course": "M13",
        "distance": 13,
        "fee": 11,
        "date": "01 June 2019",
        "club": "Muckle Cycle Club",
        "position": "60",
        "time": "0:36:39",
        "standard": "00:38:17",
        "onStandard": "-00:01:38",
        "speed": "21.28 Mph",
        "bar": 75,
        "barPosition": 46,
        "vbar": 104,
        "vbarPosition": 17,
        "wvbar": 117,
        "wvbarPosition": 4,
        "wbar": 113,
        "wbarPosition": 8,
        "rbar": 0,
        "rbarPosition": 0,
        "wrbar": 0,
        "wrbarPosition": 0
      }
    ],
    "medium": [
      {
        "eventId": "18238",
        "raceCategory": "medium",
        "name": "Barnesbury CC - Hilly 21",
        "course": "M21",
        "distance": 21,
        "fee": 10,
        "date": "30 March 2019",
        "club": "Muckle Cycle Club",
        "position": "87",
        "time": "1:07:41",
        "standard": "01:02:09",
        "onStandard": "00:05:32",
        "speed": "18.62 Mph",
        "bar": 60,
        "barPosition": 61,
        "vbar": 87,
        "vbarPosition": 34,
        "wvbar": 119,
        "wvbarPosition": 2,
        "wbar": 114,
        "wbarPosition": 7,
        "rbar": 0,
        "rbarPosition": 0,
        "wrbar": 0,
        "wrbarPosition": 0
      },
      {
        "eventId": "18246",
        "raceCategory": "medium",
        "name": "North Tyneside Riders",
        "course": "M27",
        "distance": 27,
        "fee": 11,
        "date": "07 July 2019",
        "club": "Muckle Cycle Club",
        "position": "26",
        "time": "1:41:59",
        "standard": "01:20:38",
        "onStandard": "00:21:21",
        "speed": "15.88 Mph",
        "bar": 98,
        "barPosition": 23,
        "vbar": 107,
        "vbarPosition": 14,
        "wvbar": 119,
        "wvbarPosition": 2,
        "wbar": 118,
        "wbarPosition": 3,
        "rbar": 112,
        "rbarPosition": 9,
        "wrbar": 118,
        "wrbarPosition": 3
      }
    ],
    "long": [
      {
        "eventId": "18263",
        "raceCategory": "long",
        "name": "South Shields Velo CC (N&DCA Championship) (BBAR)",
        "course": "M5011",
        "distance": 50,
        "fee": 11,
        "date": "04 August 2019",
        "club": "Muckle Cycle Club",
        "position": "53",
        "time": "2:27:20",
        "standard": "02:32:43",
        "onStandard": "-00:05:23",
        "speed": "20.36 Mph",
        "bar": 71,
        "barPosition": 50,
        "vbar": 97,
        "vbarPosition": 24,
        "wvbar": 117,
        "wvbarPosition": 4,
        "wbar": 115,
        "wbarPosition": 6,
        "rbar": 0,
        "rbarPosition": 0,
        "wrbar": 0,
        "wrbarPosition": 0
      }
    ],
    "shortCount": 3,
    "mediumCount": 2,
    "longCount": 1,
    "allCount": 6,
    "complete": true,
    "canComplete": true,
    "averagePointsPerShortRace": 117.66666666666667,
    "averagePointsPerMediumRace": 119,
    "averagePointsPerLongRace": 117,
    "averagePointsPerRace": 118,
    "remainingShortPoints": 7,
    "remainingMediumPoints": 2,
    "remainingLongPoints": 3,
    "remainingPoints": 12,
    "predictedFinalPoints": 708,
    "pointsDirection": 0,
    "regionalChampionship": {
      "raced": 2,
      "totalPoints": 117
    },
    "tieBreak": {
      "raced": 3,
      "totalPoints": 352
    },
    "totals": {
      "short": 353,
      "medium": 238,
      "long": 117,
      "grand": 708
    },
    "tags": [
      {
        "cssclass": "tag has-background-warning",
        "text": "3 x 2nd WVBAR"
      },
      {
        "cssclass": "tag has-background-warning",
        "text": "5 x 3rd WVBAR"
      },
      {
        "cssclass": "tag has-background-warning",
        "text": "12 x Top 5 WVBAR"
      },
      {
        "cssclass": "tag has-background-warning",
        "text": "13 x Top 10 WVBAR"
      },
      {
        "cssclass": "tag is-black",
        "text": "1 x DNS"
      }
    ],
    "currentPosition": 6,
    "rivals": [
      {
        "position": 1,
        "id": "775",
        "pointsDirection": 0,
        "barPredictedFinalPosition": 1,
        "name": "Venda Louise Pollock",
        "club": "Blaydon CC",
        "averagePointsPerRace": 120,
        "predictedFinalPoints": 720,
        "grandTotal": 720,
        "complete": true,
        "canComplete": true,
        "regionalChampionshipPoints": 120,
        "tieBreakPoints": 240
      },
      {
        "position": 3,
        "id": "1799",
        "pointsDirection": 0,
        "barPredictedFinalPosition": 3,
        "name": "Carrie Brookes",
        "club": "Blaydon CC",
        "averagePointsPerRace": 119.5,
        "predictedFinalPoints": 717,
        "grandTotal": 717,
        "complete": true,
        "canComplete": true,
        "regionalChampionshipPoints": 238,
        "tieBreakPoints": 238
      },
      {
        "position": 4,
        "id": "3838",
        "pointsDirection": 0,
        "barPredictedFinalPosition": 4,
        "name": "Gemma Hutchins",
        "club": "Blaydon CC",
        "averagePointsPerRace": 119.16666666666667,
        "predictedFinalPoints": 715,
        "grandTotal": 715,
        "complete": true,
        "canComplete": true,
        "regionalChampionshipPoints": 118,
        "tieBreakPoints": 237
      },
      {
        "position": 5,
        "id": "3419",
        "pointsDirection": 0,
        "barPredictedFinalPosition": 5,
        "name": "Teri Bayliss",
        "club": "Muckle Cycle Club",
        "averagePointsPerRace": 119,
        "predictedFinalPoints": 714,
        "grandTotal": 714,
        "complete": true,
        "canComplete": true,
        "regionalChampionshipPoints": 238,
        "tieBreakPoints": 237
      },
      {
        "position": 6,
        "id": "19057",
        "pointsDirection": 0,
        "barPredictedFinalPosition": 6,
        "name": "Nicola Mccoy",
        "club": "Muckle Cycle Club",
        "averagePointsPerRace": 118,
        "predictedFinalPoints": 708,
        "grandTotal": 708,
        "complete": true,
        "canComplete": true,
        "regionalChampionshipPoints": 117,
        "tieBreakPoints": 352
      },
      {
        "position": 7,
        "id": "2846",
        "pointsDirection": 0,
        "barPredictedFinalPosition": 7,
        "name": "Justine Norman",
        "club": "Breeze Bikes RT",
        "averagePointsPerRace": 116.33333333333333,
        "predictedFinalPoints": 698,
        "grandTotal": 698,
        "complete": true,
        "canComplete": true,
        "regionalChampionshipPoints": 116,
        "tieBreakPoints": 231
      },
      {
        "position": 8,
        "id": "9698",
        "pointsDirection": 0,
        "barPredictedFinalPosition": 8,
        "name": "Tracey Sample",
        "club": "Breeze Bikes RT",
        "averagePointsPerRace": 115.66666666666667,
        "predictedFinalPoints": 694,
        "grandTotal": 694,
        "complete": true,
        "canComplete": true,
        "regionalChampionshipPoints": 115,
        "tieBreakPoints": 115
      },
      {
        "position": 9,
        "id": "16749",
        "pointsDirection": 0,
        "barPredictedFinalPosition": 9,
        "name": "Jane Aston",
        "club": "Blaydon CC",
        "averagePointsPerRace": 113.83333333333333,
        "predictedFinalPoints": 683,
        "grandTotal": 683,
        "complete": true,
        "canComplete": true,
        "regionalChampionshipPoints": 0,
        "tieBreakPoints": 231
      }
    ]
  },
  "wrbar": {
    "short": [],
    "medium": [
      {
        "eventId": "18265",
        "raceCategory": "medium",
        "name": "Blaydon CC",
        "course": "M23-1",
        "distance": 23,
        "fee": 11,
        "date": "25 August 2019",
        "club": "Muckle Cycle Club",
        "position": "49",
        "time": "1:18:45",
        "standard": "01:08:25",
        "onStandard": "00:10:20",
        "speed": "17.52 Mph",
        "bar": 82,
        "barPosition": 39,
        "vbar": 98,
        "vbarPosition": 23,
        "wvbar": 118,
        "wvbarPosition": 3,
        "wbar": 116,
        "wbarPosition": 5,
        "rbar": 115,
        "rbarPosition": 6,
        "wrbar": 120,
        "wrbarPosition": 1
      },
      {
        "eventId": "18246",
        "raceCategory": "medium",
        "name": "North Tyneside Riders",
        "course": "M27",
        "distance": 27,
        "fee": 11,
        "date": "07 July 2019",
        "club": "Muckle Cycle Club",
        "position": "26",
        "time": "1:41:59",
        "standard": "01:20:38",
        "onStandard": "00:21:21",
        "speed": "15.88 Mph",
        "bar": 98,
        "barPosition": 23,
        "vbar": 107,
        "vbarPosition": 14,
        "wvbar": 119,
        "wvbarPosition": 2,
        "wbar": 118,
        "wbarPosition": 3,
        "rbar": 112,
        "rbarPosition": 9,
        "wrbar": 118,
        "wrbarPosition": 3
      }
    ],
    "long": [],
    "shortCount": 0,
    "mediumCount": 2,
    "longCount": 0,
    "allCount": 2,
    "complete": false,
    "canComplete": false,
    "averagePointsPerShortRace": 119,
    "averagePointsPerMediumRace": 119,
    "averagePointsPerLongRace": 119,
    "averagePointsPerRace": 119,
    "remainingShortPoints": 360,
    "remainingMediumPoints": 2,
    "remainingLongPoints": 120,
    "remainingPoints": 482,
    "predictedFinalPoints": 714,
    "pointsDirection": 1,
    "regionalChampionship": {
      "raced": 2,
      "totalPoints": 0
    },
    "tieBreak": {
      "raced": 3,
      "totalPoints": 118
    },
    "totals": {
      "short": 0,
      "medium": 238,
      "long": 0,
      "grand": 238
    },
    "tags": [
      {
        "cssclass": "tag has-background-warning",
        "text": "1 x 1st WRBAR"
      },
      {
        "cssclass": "tag has-background-warning",
        "text": "1 x 3rd WRBAR"
      },
      {
        "cssclass": "tag has-background-warning",
        "text": "2 x Top 5 WRBAR"
      },
      {
        "cssclass": "tag has-background-warning",
        "text": "2 x Top 10 WRBAR"
      },
      {
        "cssclass": "tag is-black",
        "text": "1 x DNS"
      }
    ],
    "currentPosition": 7,
    "rivals": [
      {
        "position": 1,
        "id": "25359",
        "pointsDirection": 0,
        "barPredictedFinalPosition": 1,
        "name": "Sarah Wilkinson",
        "club": "Blaydon CC",
        "averagePointsPerRace": 120,
        "predictedFinalPoints": 720,
        "grandTotal": 720,
        "complete": true,
        "canComplete": true,
        "regionalChampionshipPoints": 120,
        "tieBreakPoints": 120
      },
      {
        "position": 4,
        "id": "16749",
        "pointsDirection": 0,
        "barPredictedFinalPosition": 4,
        "name": "Jane Aston",
        "club": "Blaydon CC",
        "averagePointsPerRace": 118.16666666666667,
        "predictedFinalPoints": 709,
        "grandTotal": 709,
        "complete": true,
        "canComplete": true,
        "regionalChampionshipPoints": 0,
        "tieBreakPoints": 237
      },
      {
        "position": 5,
        "id": "19753",
        "pointsDirection": 0,
        "name": "Hannah Farran",
        "club": "Team Boompods",
        "averagePointsPerRace": 119.5,
        "predictedFinalPoints": 717.5,
        "grandTotal": 239,
        "complete": false,
        "canComplete": false,
        "regionalChampionshipPoints": 0,
        "tieBreakPoints": 119
      },
      {
        "position": 6,
        "id": "9329",
        "pointsDirection": -1,
        "name": "Jane Massey",
        "club": "Cramlington CC",
        "averagePointsPerRace": 119.5,
        "predictedFinalPoints": 716.5,
        "grandTotal": 239,
        "complete": false,
        "canComplete": false,
        "regionalChampionshipPoints": 120,
        "tieBreakPoints": 116
      },
      {
        "position": 7,
        "id": "19057",
        "pointsDirection": 1,
        "name": "Nicola Mccoy",
        "club": "Muckle Cycle Club",
        "averagePointsPerRace": 119,
        "predictedFinalPoints": 714,
        "grandTotal": 238,
        "complete": false,
        "canComplete": true,
        "regionalChampionshipPoints": 0,
        "tieBreakPoints": 118
      },
      {
        "position": 8,
        "id": "21755",
        "pointsDirection": 0,
        "name": "Sian Salter",
        "club": "North Tyneside Riders CC",
        "averagePointsPerRace": 117,
        "predictedFinalPoints": 702,
        "grandTotal": 234,
        "complete": false,
        "canComplete": false,
        "regionalChampionshipPoints": 0,
        "tieBreakPoints": 117
      },
      {
        "position": 9,
        "id": "16184",
        "pointsDirection": 0,
        "name": "Gemma Frost",
        "club": "Team Swift",
        "averagePointsPerRace": 120,
        "predictedFinalPoints": 720,
        "grandTotal": 120,
        "complete": false,
        "canComplete": true,
        "regionalChampionshipPoints": 0,
        "tieBreakPoints": 120
      },
      {
        "position": 10,
        "id": "3653",
        "pointsDirection": 0,
        "name": "Miriam Jessett",
        "club": "Team Kirkley Cycles",
        "averagePointsPerRace": 120,
        "predictedFinalPoints": 720,
        "grandTotal": 120,
        "complete": false,
        "canComplete": false,
        "regionalChampionshipPoints": 0,
        "tieBreakPoints": 0
      }
    ]
  },
  "rbar": {
    "short": [],
    "medium": [
      {
        "eventId": "18265",
        "raceCategory": "medium",
        "name": "Blaydon CC",
        "course": "M23-1",
        "distance": 23,
        "fee": 11,
        "date": "25 August 2019",
        "club": "Muckle Cycle Club",
        "position": "49",
        "time": "1:18:45",
        "standard": "01:08:25",
        "onStandard": "00:10:20",
        "speed": "17.52 Mph",
        "bar": 82,
        "barPosition": 39,
        "vbar": 98,
        "vbarPosition": 23,
        "wvbar": 118,
        "wvbarPosition": 3,
        "wbar": 116,
        "wbarPosition": 5,
        "rbar": 115,
        "rbarPosition": 6,
        "wrbar": 120,
        "wrbarPosition": 1
      },
      {
        "eventId": "18246",
        "raceCategory": "medium",
        "name": "North Tyneside Riders",
        "course": "M27",
        "distance": 27,
        "fee": 11,
        "date": "07 July 2019",
        "club": "Muckle Cycle Club",
        "position": "26",
        "time": "1:41:59",
        "standard": "01:20:38",
        "onStandard": "00:21:21",
        "speed": "15.88 Mph",
        "bar": 98,
        "barPosition": 23,
        "vbar": 107,
        "vbarPosition": 14,
        "wvbar": 119,
        "wvbarPosition": 2,
        "wbar": 118,
        "wbarPosition": 3,
        "rbar": 112,
        "rbarPosition": 9,
        "wrbar": 118,
        "wrbarPosition": 3
      }
    ],
    "long": [],
    "shortCount": 0,
    "mediumCount": 2,
    "longCount": 0,
    "allCount": 2,
    "complete": false,
    "canComplete": false,
    "averagePointsPerShortRace": 113.5,
    "averagePointsPerMediumRace": 113.5,
    "averagePointsPerLongRace": 113.5,
    "averagePointsPerRace": 113.5,
    "remainingShortPoints": 360,
    "remainingMediumPoints": 13,
    "remainingLongPoints": 120,
    "remainingPoints": 493,
    "predictedFinalPoints": 681,
    "pointsDirection": 1,
    "regionalChampionship": {
      "raced": 2,
      "totalPoints": 0
    },
    "tieBreak": {
      "raced": 3,
      "totalPoints": 112
    },
    "totals": {
      "short": 0,
      "medium": 227,
      "long": 0,
      "grand": 227
    },
    "tags": [
      {
        "cssclass": "tag has-background-warning",
        "text": "2 x Top 10 RBAR"
      },
      {
        "cssclass": "tag is-black",
        "text": "1 x DNS"
      }
    ],
    "currentPosition": 38,
    "rivals": [
      {
        "position": 1,
        "id": "1207",
        "pointsDirection": 0,
        "barPredictedFinalPosition": 1,
        "name": "Jonathan Bayley",
        "club": "Reifen Racing",
        "averagePointsPerRace": 120,
        "predictedFinalPoints": 720,
        "grandTotal": 720,
        "complete": true,
        "canComplete": true,
        "regionalChampionshipPoints": 239,
        "tieBreakPoints": 358
      },
      {
        "position": 35,
        "id": "5494",
        "pointsDirection": 1,
        "name": "Stephen Kerr",
        "club": "Sunderland Clarion",
        "averagePointsPerRace": 114.5,
        "predictedFinalPoints": 687,
        "grandTotal": 229,
        "complete": false,
        "canComplete": false,
        "regionalChampionshipPoints": 0,
        "tieBreakPoints": 0
      },
      {
        "position": 36,
        "id": "1711",
        "pointsDirection": 1,
        "name": "Tom Guy",
        "club": "Sunderland Clarion",
        "averagePointsPerRace": 114,
        "predictedFinalPoints": 682,
        "grandTotal": 228,
        "complete": false,
        "canComplete": false,
        "regionalChampionshipPoints": 0,
        "tieBreakPoints": 0
      },
      {
        "position": 37,
        "id": "2999",
        "pointsDirection": 1,
        "name": "Philip Green",
        "club": "GS Metro",
        "averagePointsPerRace": 114,
        "predictedFinalPoints": 684,
        "grandTotal": 228,
        "complete": false,
        "canComplete": false,
        "regionalChampionshipPoints": 0,
        "tieBreakPoints": 0
      },
      {
        "position": 38,
        "id": "19057",
        "pointsDirection": 1,
        "name": "Nicola Mccoy",
        "club": "Muckle Cycle Club",
        "averagePointsPerRace": 113.5,
        "predictedFinalPoints": 681,
        "grandTotal": 227,
        "complete": false,
        "canComplete": true,
        "regionalChampionshipPoints": 0,
        "tieBreakPoints": 112
      },
      {
        "position": 39,
        "id": "22523",
        "pointsDirection": 1,
        "name": "Chris Judson",
        "club": "North Tyneside Riders CC",
        "averagePointsPerRace": 113.5,
        "predictedFinalPoints": 681,
        "grandTotal": 227,
        "complete": false,
        "canComplete": false,
        "regionalChampionshipPoints": 0,
        "tieBreakPoints": 0
      },
      {
        "position": 40,
        "id": "18377",
        "pointsDirection": 1,
        "name": "Sean Bell",
        "club": "South Shields Velo Cycling Club",
        "averagePointsPerRace": 112.5,
        "predictedFinalPoints": 675,
        "grandTotal": 225,
        "complete": false,
        "canComplete": false,
        "regionalChampionshipPoints": 0,
        "tieBreakPoints": 112
      },
      {
        "position": 41,
        "id": "23827",
        "pointsDirection": 1,
        "name": "Bryan Ross",
        "club": "South Shields Velo Cycling Club",
        "averagePointsPerRace": 112,
        "predictedFinalPoints": 672,
        "grandTotal": 224,
        "complete": false,
        "canComplete": false,
        "regionalChampionshipPoints": 0,
        "tieBreakPoints": 116
      }
    ]
  },
  "races": [
    {
      "eventId": "18238",
      "raceCategory": "medium",
      "name": "Barnesbury CC - Hilly 21",
      "course": "M21",
      "distance": 21,
      "fee": 10,
      "date": "30 March 2019",
      "club": "Muckle Cycle Club",
      "position": "87",
      "time": "1:07:41",
      "standard": "01:02:09",
      "onStandard": "00:05:32",
      "speed": "18.62 Mph",
      "bar": 60,
      "barPosition": 61,
      "vbar": 87,
      "vbarPosition": 34,
      "wvbar": 119,
      "wvbarPosition": 2,
      "wbar": 114,
      "wbarPosition": 7,
      "rbar": 0,
      "rbarPosition": 0,
      "wrbar": 0,
      "wrbarPosition": 0
    },
    {
      "eventId": "18241",
      "raceCategory": "short",
      "name": "South Shields Velo",
      "course": "M101",
      "distance": 10,
      "fee": 11,
      "date": "20 April 2019",
      "club": "Muckle Cycle Club",
      "position": "96",
      "time": "0:26:26",
      "standard": "00:29:16",
      "onStandard": "-00:02:50",
      "speed": "22.70 Mph",
      "bar": 46,
      "barPosition": 75,
      "vbar": 82,
      "vbarPosition": 39,
      "wvbar": 116,
      "wvbarPosition": 5,
      "wbar": 111,
      "wbarPosition": 10,
      "rbar": 0,
      "rbarPosition": 0,
      "wrbar": 0,
      "wrbarPosition": 0
    },
    {
      "eventId": "18244",
      "raceCategory": "short",
      "name": "Tyne & Wear Fire Service CC",
      "course": "M12",
      "distance": 12,
      "fee": 11,
      "date": "11 May 2019",
      "club": "Muckle Cycle Club",
      "position": "67",
      "time": "0:37:35",
      "standard": "00:35:18",
      "onStandard": "00:02:17",
      "speed": "19.16 Mph",
      "bar": 68,
      "barPosition": 53,
      "vbar": 93,
      "vbarPosition": 28,
      "wvbar": 114,
      "wvbarPosition": 7,
      "wbar": 111,
      "wbarPosition": 10,
      "rbar": 0,
      "rbarPosition": 0,
      "wrbar": 0,
      "wrbarPosition": 0
    },
    {
      "eventId": "18255",
      "raceCategory": "medium",
      "name": "Gosforth Road Club (BBAR)",
      "course": "M2511",
      "distance": 25,
      "fee": 11,
      "date": "26 May 2019",
      "club": "Muckle Cycle Club",
      "position": "58",
      "time": "1:15:43",
      "standard": "01:14:31",
      "onStandard": "00:01:12",
      "speed": "19.81 Mph",
      "bar": 75,
      "barPosition": 46,
      "vbar": 96,
      "vbarPosition": 25,
      "wvbar": 116,
      "wvbarPosition": 5,
      "wbar": 113,
      "wbarPosition": 8,
      "rbar": 0,
      "rbarPosition": 0,
      "wrbar": 0,
      "wrbarPosition": 0
    },
    {
      "eventId": "18247",
      "raceCategory": "short",
      "name": "Alnwick CC",
      "course": "M13",
      "distance": 13,
      "fee": 11,
      "date": "01 June 2019",
      "club": "Muckle Cycle Club",
      "position": "60",
      "time": "0:36:39",
      "standard": "00:38:17",
      "onStandard": "-00:01:38",
      "speed": "21.28 Mph",
      "bar": 75,
      "barPosition": 46,
      "vbar": 104,
      "vbarPosition": 17,
      "wvbar": 117,
      "wvbarPosition": 4,
      "wbar": 113,
      "wbarPosition": 8,
      "rbar": 0,
      "rbarPosition": 0,
      "wrbar": 0,
      "wrbarPosition": 0
    },
    {
      "eventId": "18250",
      "raceCategory": "medium",
      "name": "Sunderland Clarion (BBAR)",
      "course": "M254",
      "distance": 25,
      "fee": 10,
      "date": "16 June 2019",
      "club": "Muckle Cycle Club",
      "position": "53",
      "time": "1:11:29",
      "standard": "01:14:31",
      "onStandard": "-00:03:02",
      "speed": "20.98 Mph",
      "bar": 77,
      "barPosition": 44,
      "vbar": 95,
      "vbarPosition": 26,
      "wvbar": 118,
      "wvbarPosition": 3,
      "wbar": 116,
      "wbarPosition": 5,
      "rbar": 0,
      "rbarPosition": 0,
      "wrbar": 0,
      "wrbarPosition": 0
    },
    {
      "eventId": "18252",
      "raceCategory": "medium",
      "name": "Houghton CC (BBAR)",
      "course": "M254",
      "distance": 25,
      "fee": 11,
      "date": "23 June 2019",
      "club": "Muckle Cycle Club",
      "position": "36",
      "time": "1:12:22",
      "standard": "01:14:31",
      "onStandard": "-00:02:09",
      "speed": "20.73 Mph",
      "bar": 87,
      "barPosition": 34,
      "vbar": 103,
      "vbarPosition": 18,
      "wvbar": 118,
      "wvbarPosition": 3,
      "wbar": 117,
      "wbarPosition": 4,
      "rbar": 0,
      "rbarPosition": 0,
      "wrbar": 0,
      "wrbarPosition": 0
    },
    {
      "eventId": "18246",
      "raceCategory": "medium",
      "name": "North Tyneside Riders",
      "course": "M27",
      "distance": 27,
      "fee": 11,
      "date": "07 July 2019",
      "club": "Muckle Cycle Club",
      "position": "26",
      "time": "1:41:59",
      "standard": "01:20:38",
      "onStandard": "00:21:21",
      "speed": "15.88 Mph",
      "bar": 98,
      "barPosition": 23,
      "vbar": 107,
      "vbarPosition": 14,
      "wvbar": 119,
      "wvbarPosition": 2,
      "wbar": 118,
      "wbarPosition": 3,
      "rbar": 112,
      "rbarPosition": 9,
      "wrbar": 118,
      "wrbarPosition": 3
    },
    {
      "eventId": "18256",
      "raceCategory": "short",
      "name": "Barnesbury CC (Cheques To B Bayne)(80 Riders)",
      "course": "M102B",
      "distance": 10,
      "fee": 10,
      "date": "10 July 2019",
      "club": "Muckle Cycle Club",
      "position": "59",
      "time": "0:25:31",
      "standard": "00:29:21",
      "onStandard": "-00:03:50",
      "speed": "23.51 Mph",
      "bar": 70,
      "barPosition": 51,
      "vbar": 99,
      "vbarPosition": 22,
      "wvbar": 118,
      "wvbarPosition": 3,
      "wbar": 116,
      "wbarPosition": 5,
      "rbar": 0,
      "rbarPosition": 0,
      "wrbar": 0,
      "wrbarPosition": 0
    },
    {
      "eventId": "18258",
      "raceCategory": "medium",
      "name": "Barnesbury CC (Inc. N&DCA 25 Championship)(Cheques To S Dyson) (BBAR)",
      "course": "M2510",
      "distance": 25,
      "fee": 11,
      "date": "22 July 2019",
      "club": "Muckle Cycle Club",
      "position": "DNS",
      "time": "",
      "standard": "",
      "onStandard": "",
      "speed": "",
      "bar": 0,
      "barPosition": 0,
      "vbar": 0,
      "vbarPosition": 0,
      "wvbar": 0,
      "wvbarPosition": 0,
      "wbar": 0,
      "wbarPosition": 0,
      "rbar": 0,
      "rbarPosition": 0,
      "wrbar": 0,
      "wrbarPosition": 0
    },
    {
      "eventId": "18260",
      "raceCategory": "medium",
      "name": "GS Metro",
      "course": "M26",
      "distance": 26,
      "fee": 11,
      "date": "27 July 2019",
      "club": "Muckle Cycle Club",
      "position": "35",
      "time": "1:19:50",
      "standard": "01:17:34",
      "onStandard": "00:02:16",
      "speed": "19.54 Mph",
      "bar": 90,
      "barPosition": 31,
      "vbar": 109,
      "vbarPosition": 12,
      "wvbar": 119,
      "wvbarPosition": 2,
      "wbar": 115,
      "wbarPosition": 6,
      "rbar": 0,
      "rbarPosition": 0,
      "wrbar": 0,
      "wrbarPosition": 0
    },
    {
      "eventId": "18263",
      "raceCategory": "long",
      "name": "South Shields Velo CC (N&DCA Championship) (BBAR)",
      "course": "M5011",
      "distance": 50,
      "fee": 11,
      "date": "04 August 2019",
      "club": "Muckle Cycle Club",
      "position": "53",
      "time": "2:27:20",
      "standard": "02:32:43",
      "onStandard": "-00:05:23",
      "speed": "20.36 Mph",
      "bar": 71,
      "barPosition": 50,
      "vbar": 97,
      "vbarPosition": 24,
      "wvbar": 117,
      "wvbarPosition": 4,
      "wbar": 115,
      "wbarPosition": 6,
      "rbar": 0,
      "rbarPosition": 0,
      "wrbar": 0,
      "wrbarPosition": 0
    },
    {
      "eventId": "18264",
      "raceCategory": "short",
      "name": "Barnesbury CC (Cheques To S Dodd)",
      "course": "M102C",
      "distance": 10,
      "fee": 10,
      "date": "18 August 2019",
      "club": "Muckle Cycle Club",
      "position": "58",
      "time": "0:28:02",
      "standard": "00:29:21",
      "onStandard": "-00:01:19",
      "speed": "21.40 Mph",
      "bar": 77,
      "barPosition": 44,
      "vbar": 99,
      "vbarPosition": 22,
      "wvbar": 118,
      "wvbarPosition": 3,
      "wbar": 114,
      "wbarPosition": 7,
      "rbar": 0,
      "rbarPosition": 0,
      "wrbar": 0,
      "wrbarPosition": 0
    },
    {
      "eventId": "18265",
      "raceCategory": "medium",
      "name": "Blaydon CC",
      "course": "M23-1",
      "distance": 23,
      "fee": 11,
      "date": "25 August 2019",
      "club": "Muckle Cycle Club",
      "position": "49",
      "time": "1:18:45",
      "standard": "01:08:25",
      "onStandard": "00:10:20",
      "speed": "17.52 Mph",
      "bar": 82,
      "barPosition": 39,
      "vbar": 98,
      "vbarPosition": 23,
      "wvbar": 118,
      "wvbarPosition": 3,
      "wbar": 116,
      "wbarPosition": 5,
      "rbar": 115,
      "rbarPosition": 6,
      "wrbar": 120,
      "wrbarPosition": 1
    }
  ],
  "barHistory": [
    {
      "eventId": "18238",
      "date": "30 March 2019",
      "name": "M21",
      "points": {
        "short": 0,
        "medium": 60,
        "long": 0,
        "grand": 60
      },
      "position": 61
    },
    {
      "eventId": "18240",
      "date": "13 April 2019",
      "name": "M102B",
      "points": {
        "short": 0,
        "medium": 60,
        "long": 0,
        "grand": 60
      },
      "position": 101
    },
    {
      "eventId": "18241",
      "date": "20 April 2019",
      "name": "M101",
      "points": {
        "short": 46,
        "medium": 60,
        "long": 0,
        "grand": 106
      },
      "position": 75
    },
    {
      "eventId": "18242",
      "date": "28 April 2019",
      "name": "M1010B",
      "points": {
        "short": 46,
        "medium": 60,
        "long": 0,
        "grand": 106
      },
      "position": 89
    },
    {
      "eventId": "18243",
      "date": "05 May 2019",
      "name": "M40",
      "points": {
        "short": 46,
        "medium": 60,
        "long": 0,
        "grand": 106
      },
      "position": 106
    },
    {
      "eventId": "18244",
      "date": "11 May 2019",
      "name": "M12",
      "points": {
        "short": 114,
        "medium": 60,
        "long": 0,
        "grand": 174
      },
      "position": 84
    },
    {
      "eventId": "18245",
      "date": "19 May 2019",
      "name": "M47",
      "points": {
        "short": 114,
        "medium": 60,
        "long": 0,
        "grand": 174
      },
      "position": 88
    },
    {
      "eventId": "18255",
      "date": "26 May 2019",
      "name": "M2511",
      "points": {
        "short": 114,
        "medium": 135,
        "long": 0,
        "grand": 249
      },
      "position": 63
    },
    {
      "eventId": "18247",
      "date": "01 June 2019",
      "name": "M13",
      "points": {
        "short": 189,
        "medium": 135,
        "long": 0,
        "grand": 324
      },
      "position": 46
    },
    {
      "eventId": "18248",
      "date": "09 June 2019",
      "name": "M24.8",
      "points": {
        "short": 189,
        "medium": 135,
        "long": 0,
        "grand": 324
      },
      "position": 51
    },
    {
      "eventId": "18250",
      "date": "16 June 2019",
      "name": "M254",
      "points": {
        "short": 189,
        "medium": 152,
        "long": 0,
        "grand": 341
      },
      "position": 50
    },
    {
      "eventId": "18251",
      "date": "22 June 2019",
      "name": "M9",
      "points": {
        "short": 189,
        "medium": 152,
        "long": 0,
        "grand": 341
      },
      "position": 59
    },
    {
      "eventId": "18252",
      "date": "23 June 2019",
      "name": "M254",
      "points": {
        "short": 189,
        "medium": 164,
        "long": 0,
        "grand": 353
      },
      "position": 60
    },
    {
      "eventId": "18253",
      "date": "29 June 2019",
      "name": "M107",
      "points": {
        "short": 189,
        "medium": 164,
        "long": 0,
        "grand": 353
      },
      "position": 67
    },
    {
      "eventId": "18246",
      "date": "07 July 2019",
      "name": "M27",
      "points": {
        "short": 189,
        "medium": 185,
        "long": 0,
        "grand": 374
      },
      "position": 62
    },
    {
      "eventId": "18256",
      "date": "10 July 2019",
      "name": "M102B",
      "points": {
        "short": 213,
        "medium": 185,
        "long": 0,
        "grand": 398
      },
      "position": 66
    },
    {
      "eventId": "18257",
      "date": "14 July 2019",
      "name": "M14",
      "points": {
        "short": 213,
        "medium": 185,
        "long": 0,
        "grand": 398
      },
      "position": 71
    },
    {
      "eventId": "18258",
      "date": "22 July 2019",
      "name": "M2510",
      "points": {
        "short": 213,
        "medium": 185,
        "long": 0,
        "grand": 398
      },
      "position": 74
    },
    {
      "eventId": "18260",
      "date": "27 July 2019",
      "name": "M26",
      "points": {
        "short": 213,
        "medium": 188,
        "long": 0,
        "grand": 401
      },
      "position": 72
    },
    {
      "eventId": "18263",
      "date": "04 August 2019",
      "name": "M5011",
      "points": {
        "short": 213,
        "medium": 188,
        "long": 71,
        "grand": 472
      },
      "position": 55
    },
    {
      "eventId": "18264",
      "date": "18 August 2019",
      "name": "M102C",
      "points": {
        "short": 222,
        "medium": 188,
        "long": 71,
        "grand": 481
      },
      "position": 55
    },
    {
      "eventId": "18265",
      "date": "25 August 2019",
      "name": "M23-1",
      "points": {
        "short": 222,
        "medium": 188,
        "long": 71,
        "grand": 481
      },
      "position": 59
    },
    {
      "eventId": "18266",
      "date": "01 September 2019",
      "name": "M100/10",
      "points": {
        "short": 222,
        "medium": 188,
        "long": 71,
        "grand": 481
      },
      "position": 59
    }
  ],
  "vbarHistory": [
    {
      "eventId": "18238",
      "date": "30 March 2019",
      "name": "M21",
      "points": {
        "short": 0,
        "medium": 87,
        "long": 0,
        "grand": 87
      },
      "position": 34
    },
    {
      "eventId": "18240",
      "date": "13 April 2019",
      "name": "M102B",
      "points": {
        "short": 0,
        "medium": 87,
        "long": 0,
        "grand": 87
      },
      "position": 57
    },
    {
      "eventId": "18241",
      "date": "20 April 2019",
      "name": "M101",
      "points": {
        "short": 82,
        "medium": 87,
        "long": 0,
        "grand": 169
      },
      "position": 36
    },
    {
      "eventId": "18242",
      "date": "28 April 2019",
      "name": "M1010B",
      "points": {
        "short": 82,
        "medium": 87,
        "long": 0,
        "grand": 169
      },
      "position": 49
    },
    {
      "eventId": "18243",
      "date": "05 May 2019",
      "name": "M40",
      "points": {
        "short": 82,
        "medium": 87,
        "long": 0,
        "grand": 169
      },
      "position": 54
    },
    {
      "eventId": "18244",
      "date": "11 May 2019",
      "name": "M12",
      "points": {
        "short": 175,
        "medium": 87,
        "long": 0,
        "grand": 262
      },
      "position": 32
    },
    {
      "eventId": "18245",
      "date": "19 May 2019",
      "name": "M47",
      "points": {
        "short": 175,
        "medium": 87,
        "long": 0,
        "grand": 262
      },
      "position": 35
    },
    {
      "eventId": "18255",
      "date": "26 May 2019",
      "name": "M2511",
      "points": {
        "short": 175,
        "medium": 183,
        "long": 0,
        "grand": 358
      },
      "position": 22
    },
    {
      "eventId": "18247",
      "date": "01 June 2019",
      "name": "M13",
      "points": {
        "short": 279,
        "medium": 183,
        "long": 0,
        "grand": 462
      },
      "position": 14
    },
    {
      "eventId": "18248",
      "date": "09 June 2019",
      "name": "M24.8",
      "points": {
        "short": 279,
        "medium": 183,
        "long": 0,
        "grand": 462
      },
      "position": 18
    },
    {
      "eventId": "18250",
      "date": "16 June 2019",
      "name": "M254",
      "points": {
        "short": 279,
        "medium": 191,
        "long": 0,
        "grand": 470
      },
      "position": 19
    },
    {
      "eventId": "18251",
      "date": "22 June 2019",
      "name": "M9",
      "points": {
        "short": 279,
        "medium": 191,
        "long": 0,
        "grand": 470
      },
      "position": 22
    },
    {
      "eventId": "18252",
      "date": "23 June 2019",
      "name": "M254",
      "points": {
        "short": 279,
        "medium": 199,
        "long": 0,
        "grand": 478
      },
      "position": 25
    },
    {
      "eventId": "18253",
      "date": "29 June 2019",
      "name": "M107",
      "points": {
        "short": 279,
        "medium": 199,
        "long": 0,
        "grand": 478
      },
      "position": 29
    },
    {
      "eventId": "18246",
      "date": "07 July 2019",
      "name": "M27",
      "points": {
        "short": 279,
        "medium": 210,
        "long": 0,
        "grand": 489
      },
      "position": 29
    },
    {
      "eventId": "18256",
      "date": "10 July 2019",
      "name": "M102B",
      "points": {
        "short": 296,
        "medium": 210,
        "long": 0,
        "grand": 506
      },
      "position": 32
    },
    {
      "eventId": "18257",
      "date": "14 July 2019",
      "name": "M14",
      "points": {
        "short": 296,
        "medium": 210,
        "long": 0,
        "grand": 506
      },
      "position": 33
    },
    {
      "eventId": "18258",
      "date": "22 July 2019",
      "name": "M2510",
      "points": {
        "short": 296,
        "medium": 210,
        "long": 0,
        "grand": 506
      },
      "position": 36
    },
    {
      "eventId": "18260",
      "date": "27 July 2019",
      "name": "M26",
      "points": {
        "short": 296,
        "medium": 216,
        "long": 0,
        "grand": 512
      },
      "position": 36
    },
    {
      "eventId": "18263",
      "date": "04 August 2019",
      "name": "M5011",
      "points": {
        "short": 296,
        "medium": 216,
        "long": 97,
        "grand": 609
      },
      "position": 25
    },
    {
      "eventId": "18264",
      "date": "18 August 2019",
      "name": "M102C",
      "points": {
        "short": 302,
        "medium": 216,
        "long": 97,
        "grand": 615
      },
      "position": 24
    },
    {
      "eventId": "18265",
      "date": "25 August 2019",
      "name": "M23-1",
      "points": {
        "short": 302,
        "medium": 216,
        "long": 97,
        "grand": 615
      },
      "position": 27
    },
    {
      "eventId": "18266",
      "date": "01 September 2019",
      "name": "M100/10",
      "points": {
        "short": 302,
        "medium": 216,
        "long": 97,
        "grand": 615
      },
      "position": 28
    }
  ],
  "wvbarHistory": [
    {
      "eventId": "18238",
      "date": "30 March 2019",
      "name": "M21",
      "points": {
        "short": 0,
        "medium": 119,
        "long": 0,
        "grand": 119
      },
      "position": 2
    },
    {
      "eventId": "18240",
      "date": "13 April 2019",
      "name": "M102B",
      "points": {
        "short": 0,
        "medium": 119,
        "long": 0,
        "grand": 119
      },
      "position": 3
    },
    {
      "eventId": "18241",
      "date": "20 April 2019",
      "name": "M101",
      "points": {
        "short": 116,
        "medium": 119,
        "long": 0,
        "grand": 235
      },
      "position": 4
    },
    {
      "eventId": "18242",
      "date": "28 April 2019",
      "name": "M1010B",
      "points": {
        "short": 116,
        "medium": 119,
        "long": 0,
        "grand": 235
      },
      "position": 5
    },
    {
      "eventId": "18243",
      "date": "05 May 2019",
      "name": "M40",
      "points": {
        "short": 116,
        "medium": 119,
        "long": 0,
        "grand": 235
      },
      "position": 6
    },
    {
      "eventId": "18244",
      "date": "11 May 2019",
      "name": "M12",
      "points": {
        "short": 230,
        "medium": 119,
        "long": 0,
        "grand": 349
      },
      "position": 4
    },
    {
      "eventId": "18245",
      "date": "19 May 2019",
      "name": "M47",
      "points": {
        "short": 230,
        "medium": 119,
        "long": 0,
        "grand": 349
      },
      "position": 4
    },
    {
      "eventId": "18255",
      "date": "26 May 2019",
      "name": "M2511",
      "points": {
        "short": 230,
        "medium": 235,
        "long": 0,
        "grand": 465
      },
      "position": 3
    },
    {
      "eventId": "18247",
      "date": "01 June 2019",
      "name": "M13",
      "points": {
        "short": 347,
        "medium": 235,
        "long": 0,
        "grand": 582
      },
      "position": 2
    },
    {
      "eventId": "18248",
      "date": "09 June 2019",
      "name": "M24.8",
      "points": {
        "short": 347,
        "medium": 235,
        "long": 0,
        "grand": 582
      },
      "position": 3
    },
    {
      "eventId": "18250",
      "date": "16 June 2019",
      "name": "M254",
      "points": {
        "short": 347,
        "medium": 237,
        "long": 0,
        "grand": 584
      },
      "position": 3
    },
    {
      "eventId": "18251",
      "date": "22 June 2019",
      "name": "M9",
      "points": {
        "short": 347,
        "medium": 237,
        "long": 0,
        "grand": 584
      },
      "position": 5
    },
    {
      "eventId": "18252",
      "date": "23 June 2019",
      "name": "M254",
      "points": {
        "short": 347,
        "medium": 237,
        "long": 0,
        "grand": 584
      },
      "position": 6
    },
    {
      "eventId": "18253",
      "date": "29 June 2019",
      "name": "M107",
      "points": {
        "short": 347,
        "medium": 237,
        "long": 0,
        "grand": 584
      },
      "position": 6
    },
    {
      "eventId": "18246",
      "date": "07 July 2019",
      "name": "M27",
      "points": {
        "short": 347,
        "medium": 238,
        "long": 0,
        "grand": 585
      },
      "position": 6
    },
    {
      "eventId": "18256",
      "date": "10 July 2019",
      "name": "M102B",
      "points": {
        "short": 351,
        "medium": 238,
        "long": 0,
        "grand": 589
      },
      "position": 5
    },
    {
      "eventId": "18257",
      "date": "14 July 2019",
      "name": "M14",
      "points": {
        "short": 351,
        "medium": 238,
        "long": 0,
        "grand": 589
      },
      "position": 6
    },
    {
      "eventId": "18258",
      "date": "22 July 2019",
      "name": "M2510",
      "points": {
        "short": 351,
        "medium": 238,
        "long": 0,
        "grand": 589
      },
      "position": 6
    },
    {
      "eventId": "18260",
      "date": "27 July 2019",
      "name": "M26",
      "points": {
        "short": 351,
        "medium": 238,
        "long": 0,
        "grand": 589
      },
      "position": 6
    },
    {
      "eventId": "18263",
      "date": "04 August 2019",
      "name": "M5011",
      "points": {
        "short": 351,
        "medium": 238,
        "long": 117,
        "grand": 706
      },
      "position": 4
    },
    {
      "eventId": "18264",
      "date": "18 August 2019",
      "name": "M102C",
      "points": {
        "short": 353,
        "medium": 238,
        "long": 117,
        "grand": 708
      },
      "position": 4
    },
    {
      "eventId": "18265",
      "date": "25 August 2019",
      "name": "M23-1",
      "points": {
        "short": 353,
        "medium": 238,
        "long": 117,
        "grand": 708
      },
      "position": 6
    },
    {
      "eventId": "18266",
      "date": "01 September 2019",
      "name": "M100/10",
      "points": {
        "short": 353,
        "medium": 238,
        "long": 117,
        "grand": 708
      },
      "position": 6
    }
  ],
  "wbarHistory": [
    {
      "eventId": "18238",
      "date": "30 March 2019",
      "name": "M21",
      "points": {
        "short": 0,
        "medium": 114,
        "long": 0,
        "grand": 114
      },
      "position": 7
    },
    {
      "eventId": "18240",
      "date": "13 April 2019",
      "name": "M102B",
      "points": {
        "short": 0,
        "medium": 114,
        "long": 0,
        "grand": 114
      },
      "position": 11
    },
    {
      "eventId": "18241",
      "date": "20 April 2019",
      "name": "M101",
      "points": {
        "short": 111,
        "medium": 114,
        "long": 0,
        "grand": 225
      },
      "position": 8
    },
    {
      "eventId": "18242",
      "date": "28 April 2019",
      "name": "M1010B",
      "points": {
        "short": 111,
        "medium": 114,
        "long": 0,
        "grand": 225
      },
      "position": 12
    },
    {
      "eventId": "18243",
      "date": "05 May 2019",
      "name": "M40",
      "points": {
        "short": 111,
        "medium": 114,
        "long": 0,
        "grand": 225
      },
      "position": 15
    },
    {
      "eventId": "18244",
      "date": "11 May 2019",
      "name": "M12",
      "points": {
        "short": 222,
        "medium": 114,
        "long": 0,
        "grand": 336
      },
      "position": 9
    },
    {
      "eventId": "18245",
      "date": "19 May 2019",
      "name": "M47",
      "points": {
        "short": 222,
        "medium": 114,
        "long": 0,
        "grand": 336
      },
      "position": 9
    },
    {
      "eventId": "18255",
      "date": "26 May 2019",
      "name": "M2511",
      "points": {
        "short": 222,
        "medium": 227,
        "long": 0,
        "grand": 449
      },
      "position": 6
    },
    {
      "eventId": "18247",
      "date": "01 June 2019",
      "name": "M13",
      "points": {
        "short": 335,
        "medium": 227,
        "long": 0,
        "grand": 562
      },
      "position": 4
    },
    {
      "eventId": "18248",
      "date": "09 June 2019",
      "name": "M24.8",
      "points": {
        "short": 335,
        "medium": 227,
        "long": 0,
        "grand": 562
      },
      "position": 5
    },
    {
      "eventId": "18250",
      "date": "16 June 2019",
      "name": "M254",
      "points": {
        "short": 335,
        "medium": 230,
        "long": 0,
        "grand": 565
      },
      "position": 5
    },
    {
      "eventId": "18251",
      "date": "22 June 2019",
      "name": "M9",
      "points": {
        "short": 335,
        "medium": 230,
        "long": 0,
        "grand": 565
      },
      "position": 8
    },
    {
      "eventId": "18252",
      "date": "23 June 2019",
      "name": "M254",
      "points": {
        "short": 335,
        "medium": 233,
        "long": 0,
        "grand": 568
      },
      "position": 9
    },
    {
      "eventId": "18253",
      "date": "29 June 2019",
      "name": "M107",
      "points": {
        "short": 335,
        "medium": 233,
        "long": 0,
        "grand": 568
      },
      "position": 9
    },
    {
      "eventId": "18246",
      "date": "07 July 2019",
      "name": "M27",
      "points": {
        "short": 335,
        "medium": 235,
        "long": 0,
        "grand": 570
      },
      "position": 10
    },
    {
      "eventId": "18256",
      "date": "10 July 2019",
      "name": "M102B",
      "points": {
        "short": 340,
        "medium": 235,
        "long": 0,
        "grand": 575
      },
      "position": 10
    },
    {
      "eventId": "18257",
      "date": "14 July 2019",
      "name": "M14",
      "points": {
        "short": 340,
        "medium": 235,
        "long": 0,
        "grand": 575
      },
      "position": 10
    },
    {
      "eventId": "18258",
      "date": "22 July 2019",
      "name": "M2510",
      "points": {
        "short": 340,
        "medium": 235,
        "long": 0,
        "grand": 575
      },
      "position": 10
    },
    {
      "eventId": "18260",
      "date": "27 July 2019",
      "name": "M26",
      "points": {
        "short": 340,
        "medium": 235,
        "long": 0,
        "grand": 575
      },
      "position": 10
    },
    {
      "eventId": "18263",
      "date": "04 August 2019",
      "name": "M5011",
      "points": {
        "short": 340,
        "medium": 235,
        "long": 115,
        "grand": 690
      },
      "position": 8
    },
    {
      "eventId": "18264",
      "date": "18 August 2019",
      "name": "M102C",
      "points": {
        "short": 343,
        "medium": 235,
        "long": 115,
        "grand": 693
      },
      "position": 8
    },
    {
      "eventId": "18265",
      "date": "25 August 2019",
      "name": "M23-1",
      "points": {
        "short": 343,
        "medium": 235,
        "long": 115,
        "grand": 693
      },
      "position": 10
    },
    {
      "eventId": "18266",
      "date": "01 September 2019",
      "name": "M100/10",
      "points": {
        "short": 343,
        "medium": 235,
        "long": 115,
        "grand": 693
      },
      "position": 10
    }
  ],
  "rbarHistory": [
    {
      "eventId": "18238",
      "date": "30 March 2019",
      "name": "M21",
      "points": {
        "short": 0,
        "medium": 0,
        "long": 0,
        "grand": 0
      },
      "position": 31
    },
    {
      "eventId": "18240",
      "date": "13 April 2019",
      "name": "M102B",
      "points": {
        "short": 0,
        "medium": 0,
        "long": 0,
        "grand": 0
      },
      "position": 42
    },
    {
      "eventId": "18241",
      "date": "20 April 2019",
      "name": "M101",
      "points": {
        "short": 0,
        "medium": 0,
        "long": 0,
        "grand": 0
      },
      "position": 50
    },
    {
      "eventId": "18242",
      "date": "28 April 2019",
      "name": "M1010B",
      "points": {
        "short": 0,
        "medium": 0,
        "long": 0,
        "grand": 0
      },
      "position": 52
    },
    {
      "eventId": "18243",
      "date": "05 May 2019",
      "name": "M40",
      "points": {
        "short": 0,
        "medium": 0,
        "long": 0,
        "grand": 0
      },
      "position": 66
    },
    {
      "eventId": "18244",
      "date": "11 May 2019",
      "name": "M12",
      "points": {
        "short": 0,
        "medium": 0,
        "long": 0,
        "grand": 0
      },
      "position": 70
    },
    {
      "eventId": "18245",
      "date": "19 May 2019",
      "name": "M47",
      "points": {
        "short": 0,
        "medium": 0,
        "long": 0,
        "grand": 0
      },
      "position": 83
    },
    {
      "eventId": "18255",
      "date": "26 May 2019",
      "name": "M2511",
      "points": {
        "short": 0,
        "medium": 0,
        "long": 0,
        "grand": 0
      },
      "position": 85
    },
    {
      "eventId": "18247",
      "date": "01 June 2019",
      "name": "M13",
      "points": {
        "short": 0,
        "medium": 0,
        "long": 0,
        "grand": 0
      },
      "position": 89
    },
    {
      "eventId": "18248",
      "date": "09 June 2019",
      "name": "M24.8",
      "points": {
        "short": 0,
        "medium": 0,
        "long": 0,
        "grand": 0
      },
      "position": 100
    },
    {
      "eventId": "18250",
      "date": "16 June 2019",
      "name": "M254",
      "points": {
        "short": 0,
        "medium": 0,
        "long": 0,
        "grand": 0
      },
      "position": 102
    },
    {
      "eventId": "18251",
      "date": "22 June 2019",
      "name": "M9",
      "points": {
        "short": 0,
        "medium": 0,
        "long": 0,
        "grand": 0
      },
      "position": 103
    },
    {
      "eventId": "18252",
      "date": "23 June 2019",
      "name": "M254",
      "points": {
        "short": 0,
        "medium": 0,
        "long": 0,
        "grand": 0
      },
      "position": 103
    },
    {
      "eventId": "18253",
      "date": "29 June 2019",
      "name": "M107",
      "points": {
        "short": 0,
        "medium": 0,
        "long": 0,
        "grand": 0
      },
      "position": 104
    },
    {
      "eventId": "18246",
      "date": "07 July 2019",
      "name": "M27",
      "points": {
        "short": 0,
        "medium": 112,
        "long": 0,
        "grand": 112
      },
      "position": 69
    },
    {
      "eventId": "18256",
      "date": "10 July 2019",
      "name": "M102B",
      "points": {
        "short": 0,
        "medium": 112,
        "long": 0,
        "grand": 112
      },
      "position": 69
    },
    {
      "eventId": "18257",
      "date": "14 July 2019",
      "name": "M14",
      "points": {
        "short": 0,
        "medium": 112,
        "long": 0,
        "grand": 112
      },
      "position": 71
    },
    {
      "eventId": "18258",
      "date": "22 July 2019",
      "name": "M2510",
      "points": {
        "short": 0,
        "medium": 112,
        "long": 0,
        "grand": 112
      },
      "position": 71
    },
    {
      "eventId": "18260",
      "date": "27 July 2019",
      "name": "M26",
      "points": {
        "short": 0,
        "medium": 112,
        "long": 0,
        "grand": 112
      },
      "position": 75
    },
    {
      "eventId": "18263",
      "date": "04 August 2019",
      "name": "M5011",
      "points": {
        "short": 0,
        "medium": 112,
        "long": 0,
        "grand": 112
      },
      "position": 77
    },
    {
      "eventId": "18264",
      "date": "18 August 2019",
      "name": "M102C",
      "points": {
        "short": 0,
        "medium": 112,
        "long": 0,
        "grand": 112
      },
      "position": 77
    },
    {
      "eventId": "18265",
      "date": "25 August 2019",
      "name": "M23-1",
      "points": {
        "short": 0,
        "medium": 227,
        "long": 0,
        "grand": 227
      },
      "position": 37
    },
    {
      "eventId": "18266",
      "date": "01 September 2019",
      "name": "M100/10",
      "points": {
        "short": 0,
        "medium": 227,
        "long": 0,
        "grand": 227
      },
      "position": 38
    }
  ],
  "wrbarHistory": [
    {
      "eventId": "18238",
      "date": "30 March 2019",
      "name": "M21",
      "points": {
        "short": 0,
        "medium": 0,
        "long": 0,
        "grand": 0
      },
      "position": 4
    },
    {
      "eventId": "18240",
      "date": "13 April 2019",
      "name": "M102B",
      "points": {
        "short": 0,
        "medium": 0,
        "long": 0,
        "grand": 0
      },
      "position": 4
    },
    {
      "eventId": "18241",
      "date": "20 April 2019",
      "name": "M101",
      "points": {
        "short": 0,
        "medium": 0,
        "long": 0,
        "grand": 0
      },
      "position": 5
    },
    {
      "eventId": "18242",
      "date": "28 April 2019",
      "name": "M1010B",
      "points": {
        "short": 0,
        "medium": 0,
        "long": 0,
        "grand": 0
      },
      "position": 6
    },
    {
      "eventId": "18243",
      "date": "05 May 2019",
      "name": "M40",
      "points": {
        "short": 0,
        "medium": 0,
        "long": 0,
        "grand": 0
      },
      "position": 8
    },
    {
      "eventId": "18244",
      "date": "11 May 2019",
      "name": "M12",
      "points": {
        "short": 0,
        "medium": 0,
        "long": 0,
        "grand": 0
      },
      "position": 10
    },
    {
      "eventId": "18245",
      "date": "19 May 2019",
      "name": "M47",
      "points": {
        "short": 0,
        "medium": 0,
        "long": 0,
        "grand": 0
      },
      "position": 12
    },
    {
      "eventId": "18255",
      "date": "26 May 2019",
      "name": "M2511",
      "points": {
        "short": 0,
        "medium": 0,
        "long": 0,
        "grand": 0
      },
      "position": 12
    },
    {
      "eventId": "18247",
      "date": "01 June 2019",
      "name": "M13",
      "points": {
        "short": 0,
        "medium": 0,
        "long": 0,
        "grand": 0
      },
      "position": 13
    },
    {
      "eventId": "18248",
      "date": "09 June 2019",
      "name": "M24.8",
      "points": {
        "short": 0,
        "medium": 0,
        "long": 0,
        "grand": 0
      },
      "position": 15
    },
    {
      "eventId": "18250",
      "date": "16 June 2019",
      "name": "M254",
      "points": {
        "short": 0,
        "medium": 0,
        "long": 0,
        "grand": 0
      },
      "position": 15
    },
    {
      "eventId": "18251",
      "date": "22 June 2019",
      "name": "M9",
      "points": {
        "short": 0,
        "medium": 0,
        "long": 0,
        "grand": 0
      },
      "position": 15
    },
    {
      "eventId": "18252",
      "date": "23 June 2019",
      "name": "M254",
      "points": {
        "short": 0,
        "medium": 0,
        "long": 0,
        "grand": 0
      },
      "position": 15
    },
    {
      "eventId": "18253",
      "date": "29 June 2019",
      "name": "M107",
      "points": {
        "short": 0,
        "medium": 0,
        "long": 0,
        "grand": 0
      },
      "position": 15
    },
    {
      "eventId": "18246",
      "date": "07 July 2019",
      "name": "M27",
      "points": {
        "short": 0,
        "medium": 118,
        "long": 0,
        "grand": 118
      },
      "position": 11
    },
    {
      "eventId": "18256",
      "date": "10 July 2019",
      "name": "M102B",
      "points": {
        "short": 0,
        "medium": 118,
        "long": 0,
        "grand": 118
      },
      "position": 11
    },
    {
      "eventId": "18257",
      "date": "14 July 2019",
      "name": "M14",
      "points": {
        "short": 0,
        "medium": 118,
        "long": 0,
        "grand": 118
      },
      "position": 11
    },
    {
      "eventId": "18258",
      "date": "22 July 2019",
      "name": "M2510",
      "points": {
        "short": 0,
        "medium": 118,
        "long": 0,
        "grand": 118
      },
      "position": 11
    },
    {
      "eventId": "18260",
      "date": "27 July 2019",
      "name": "M26",
      "points": {
        "short": 0,
        "medium": 118,
        "long": 0,
        "grand": 118
      },
      "position": 11
    },
    {
      "eventId": "18263",
      "date": "04 August 2019",
      "name": "M5011",
      "points": {
        "short": 0,
        "medium": 118,
        "long": 0,
        "grand": 118
      },
      "position": 11
    },
    {
      "eventId": "18264",
      "date": "18 August 2019",
      "name": "M102C",
      "points": {
        "short": 0,
        "medium": 118,
        "long": 0,
        "grand": 118
      },
      "position": 11
    },
    {
      "eventId": "18265",
      "date": "25 August 2019",
      "name": "M23-1",
      "points": {
        "short": 0,
        "medium": 238,
        "long": 0,
        "grand": 238
      },
      "position": 6
    },
    {
      "eventId": "18266",
      "date": "01 September 2019",
      "name": "M100/10",
      "points": {
        "short": 0,
        "medium": 238,
        "long": 0,
        "grand": 238
      },
      "position": 7
    }
  ]
}